{"paragraphs":[{"text":"%md\n# Linear Regression and Correlation\n\n## Challenge 1\n\nYou are the owner of a big company and you suspect that the younger your employees are, the most likely it is that they don't come to work. In order to prove this hypothesis, you have gathered some data:\n\n| EmployeeID | Age | Absences |\n|--------|-----|------------|\n| 1      | 27  | 15         |\n| 2      | 61  | 6          |\n| 3      | 37  | 10         |\n| 4      | 23  | 18         |\n| 5      | 46  |  9         |\n| 6      | 58  |  7         |\n| 7      | 29  | 14         |\n| 8      | 36  | 11         |\n| 9      | 64  |  5         |\n| 10     | 40  |  8         |\n\nYou can find this data in Ironhack's database:\ndb: `employees`\ntable: `absences`\n\nImport the necessary libraries to complete the lab here:","user":"anonymous","dateUpdated":"2019-07-21T11:00:17+0200","config":{"tableHide":false,"editorSetting":{"language":"markdown","editOnDblClick":true,"completionSupport":false},"colWidth":12,"editorMode":"ace/mode/markdown","fontSize":9,"editorHide":true,"results":{},"enabled":true},"settings":{"params":{},"forms":{}},"results":{"code":"SUCCESS","msg":[{"type":"HTML","data":"<div class=\"markdown-body\">\n<h1>Linear Regression and Correlation</h1>\n<h2>Challenge 1</h2>\n<p>You are the owner of a big company and you suspect that the younger your employees are, the most likely it is that they don&rsquo;t come to work. In order to prove this hypothesis, you have gathered some data:</p>\n<table>\n  <thead>\n    <tr>\n      <th>EmployeeID </th>\n      <th>Age </th>\n      <th>Absences </th>\n    </tr>\n  </thead>\n  <tbody>\n    <tr>\n      <td>1 </td>\n      <td>27 </td>\n      <td>15 </td>\n    </tr>\n    <tr>\n      <td>2 </td>\n      <td>61 </td>\n      <td>6 </td>\n    </tr>\n    <tr>\n      <td>3 </td>\n      <td>37 </td>\n      <td>10 </td>\n    </tr>\n    <tr>\n      <td>4 </td>\n      <td>23 </td>\n      <td>18 </td>\n    </tr>\n    <tr>\n      <td>5 </td>\n      <td>46 </td>\n      <td>9 </td>\n    </tr>\n    <tr>\n      <td>6 </td>\n      <td>58 </td>\n      <td>7 </td>\n    </tr>\n    <tr>\n      <td>7 </td>\n      <td>29 </td>\n      <td>14 </td>\n    </tr>\n    <tr>\n      <td>8 </td>\n      <td>36 </td>\n      <td>11 </td>\n    </tr>\n    <tr>\n      <td>9 </td>\n      <td>64 </td>\n      <td>5 </td>\n    </tr>\n    <tr>\n      <td>10 </td>\n      <td>40 </td>\n      <td>8 </td>\n    </tr>\n  </tbody>\n</table>\n<p>You can find this data in Ironhack&rsquo;s database:<br/>db: <code>employees</code><br/>table: <code>absences</code></p>\n<p>Import the necessary libraries to complete the lab here:</p>\n</div>"}]},"apps":[],"jobName":"paragraph_1563699617460_-583135358","id":"20190626-095154_672523881","dateCreated":"2019-07-21T11:00:17+0200","status":"READY","errorMessage":"","progressUpdateIntervalMs":500,"focus":true,"$$hashKey":"object:6043"},{"text":"import pandas as pd\nabsences = pd.read_csv(\"M2/lab-linear-regression-correlation/your-code/absences.csv\")","user":"anonymous","dateUpdated":"2019-07-22T18:23:40+0200","config":{"colWidth":12,"fontSize":9,"enabled":true,"results":{},"editorSetting":{"language":"python","editOnDblClick":false,"completionSupport":true},"editorMode":"ace/mode/python"},"settings":{"params":{},"forms":{}},"results":{"code":"SUCCESS","msg":[]},"apps":[],"jobName":"paragraph_1563803448491_55392658","id":"20190722-155048_1214276611","dateCreated":"2019-07-22T15:50:48+0200","dateStarted":"2019-07-22T18:23:40+0200","dateFinished":"2019-07-22T18:23:40+0200","status":"FINISHED","progressUpdateIntervalMs":500,"$$hashKey":"object:6044"},{"text":"group_abs = absences.groupby(by='Age', as_index=False).sum()\ngroup_abs","user":"anonymous","dateUpdated":"2019-07-22T18:23:45+0200","config":{"colWidth":12,"fontSize":9,"enabled":true,"results":{},"editorSetting":{"language":"python","editOnDblClick":false,"completionSupport":true},"editorMode":"ace/mode/python"},"settings":{"params":{},"forms":{}},"results":{"code":"SUCCESS","msg":[{"type":"TEXT","data":"   Age  Unnamed: 0  EmployeeID  Absences\n0   23           3           4        18\n1   27           0           1        15\n2   29           6           7        14\n3   36           7           8        11\n4   37           2           3        10\n5   40           9          10         8\n6   46           4           5         9\n7   58           5           6         7\n8   61           1           2         6\n9   64           8           9         5\n"}]},"apps":[],"jobName":"paragraph_1563700121885_1913188885","id":"20190721-110841_1872264172","dateCreated":"2019-07-21T11:08:41+0200","dateStarted":"2019-07-22T18:23:45+0200","dateFinished":"2019-07-22T18:23:45+0200","status":"FINISHED","progressUpdateIntervalMs":500,"$$hashKey":"object:6045"},{"text":"%md\n#### 1. Plot the scatter chart of `Age` and `Absences`. Comment the result. Do you see any relation between `Age` and `Absences`?\nYes, there is a negative correlation.","user":"anonymous","dateUpdated":"2019-07-22T18:24:09+0200","config":{"tableHide":false,"editorSetting":{"language":"markdown","editOnDblClick":true,"completionSupport":false},"colWidth":12,"editorMode":"ace/mode/markdown","fontSize":9,"editorHide":true,"results":{},"enabled":true},"settings":{"params":{},"forms":{}},"results":{"code":"SUCCESS","msg":[{"type":"HTML","data":"<div class=\"markdown-body\">\n<h4>1. Plot the scatter chart of <code>Age</code> and <code>Absences</code>. Comment the result. Do you see any relation between <code>Age</code> and <code>Absences</code>?</h4>\n<p>Yes, there is a negative correlation.</p>\n</div>"}]},"apps":[],"jobName":"paragraph_1563699617467_-1099103073","id":"20190626-152945_953023463","dateCreated":"2019-07-21T11:00:17+0200","dateStarted":"2019-07-22T18:24:09+0200","dateFinished":"2019-07-22T18:24:12+0200","status":"FINISHED","progressUpdateIntervalMs":500,"$$hashKey":"object:6046"},{"text":"%sql\nSELECT * FROM group_abs\n","user":"anonymous","dateUpdated":"2019-07-21T19:50:34+0200","config":{"editorSetting":{"language":"sql","editOnDblClick":false,"completionSupport":false,"completionKey":"TAB"},"colWidth":12,"editorMode":"ace/mode/sql","fontSize":9,"results":{"0":{"graph":{"mode":"scatterChart","height":300,"optionOpen":false,"setting":{"table":{"tableGridState":{},"tableColumnTypeState":{"names":{"Age":"string","sum(Absences)":"string"},"updated":false},"tableOptionSpecHash":"[{\"name\":\"useFilter\",\"valueType\":\"boolean\",\"defaultValue\":false,\"widget\":\"checkbox\",\"description\":\"Enable filter for columns\"},{\"name\":\"showPagination\",\"valueType\":\"boolean\",\"defaultValue\":false,\"widget\":\"checkbox\",\"description\":\"Enable pagination for better navigation\"},{\"name\":\"showAggregationFooter\",\"valueType\":\"boolean\",\"defaultValue\":false,\"widget\":\"checkbox\",\"description\":\"Enable a footer for displaying aggregated values\"}]","tableOptionValue":{"useFilter":false,"showPagination":false,"showAggregationFooter":false},"updated":false,"initialized":false},"scatterChart":{"xAxis":{"name":"Age","index":0,"aggr":"sum"},"yAxis":{"name":"Absences","index":1,"aggr":"sum"}}}},"helium":{}}},"enabled":true},"settings":{"params":{},"forms":{}},"results":{"code":"SUCCESS","msg":[{"type":"TABLE","data":"Age\tAbsences\n23\t18\n27\t15\n29\t14\n36\t11\n37\t10\n40\t8\n46\t9\n58\t7\n61\t6\n64\t5\n"}]},"apps":[],"jobName":"paragraph_1563699617468_727776004","id":"20190626-114900_1392014117","dateCreated":"2019-07-21T11:00:17+0200","dateStarted":"2019-07-21T19:42:47+0200","dateFinished":"2019-07-21T19:42:48+0200","status":"FINISHED","progressUpdateIntervalMs":500,"$$hashKey":"object:6047"},{"text":"%md\n#### 2.- Define a function to calculate the slope and intercept of the regression line for two variables. Your are not allowed to use any functions or methods that directly calculate those parameters.  ","user":"anonymous","dateUpdated":"2019-07-21T11:00:17+0200","config":{"tableHide":false,"editorSetting":{"language":"markdown","editOnDblClick":true,"completionSupport":false},"colWidth":12,"editorMode":"ace/mode/markdown","fontSize":9,"editorHide":true,"results":{},"enabled":true},"settings":{"params":{},"forms":{}},"results":{"code":"SUCCESS","msg":[{"type":"HTML","data":"<div class=\"markdown-body\">\n<h4>2.- Define a function to calculate the slope and intercept of the regression line for two variables. Your are not allowed to use any functions or methods that directly calculate those parameters.</h4>\n</div>"}]},"apps":[],"jobName":"paragraph_1563699617470_-1645187469","id":"20190626-095626_1554205948","dateCreated":"2019-07-21T11:00:17+0200","status":"READY","errorMessage":"","progressUpdateIntervalMs":500,"$$hashKey":"object:6048"},{"text":"def slope(df):\n    return df.corr()['Age']['Absences'] * (df['Absences'].std()/df['Age'].std())\n    \nslope(group_abs)","user":"anonymous","dateUpdated":"2019-07-22T18:41:14+0200","config":{"editorSetting":{"language":"python","editOnDblClick":false,"completionSupport":true,"completionKey":"TAB"},"colWidth":12,"editorMode":"ace/mode/python","fontSize":9,"results":{},"enabled":true},"settings":{"params":{},"forms":{}},"results":{"code":"SUCCESS","msg":[{"type":"TEXT","data":"-0.26810883370334043\n"}]},"apps":[],"jobName":"paragraph_1563699617470_-1346956006","id":"20190626-114901_2139527879","dateCreated":"2019-07-21T11:00:17+0200","dateStarted":"2019-07-22T18:41:14+0200","dateFinished":"2019-07-22T18:41:14+0200","status":"FINISHED","progressUpdateIntervalMs":500,"$$hashKey":"object:6049"},{"text":"%md\n#### 3.- Use the function you defined in step 2 to calculate the regression line for `Age` and `Absences`. Plot it and comment your results.","user":"anonymous","dateUpdated":"2019-07-21T11:00:17+0200","config":{"tableHide":false,"editorSetting":{"language":"markdown","editOnDblClick":true,"completionSupport":false},"colWidth":12,"editorMode":"ace/mode/markdown","fontSize":9,"editorHide":true,"results":{},"enabled":true},"settings":{"params":{},"forms":{}},"results":{"code":"SUCCESS","msg":[{"type":"HTML","data":"<div class=\"markdown-body\">\n<h4>3.- Use the function you defined in step 2 to calculate the regression line for <code>Age</code> and <code>Absences</code>. Plot it and comment your results.</h4>\n</div>"}]},"apps":[],"jobName":"paragraph_1563699617472_1465121149","id":"20190626-114707_1617000297","dateCreated":"2019-07-21T11:00:17+0200","status":"READY","errorMessage":"","progressUpdateIntervalMs":500,"$$hashKey":"object:6050"},{"text":"def n(df):\n    return df['Absences'].mean() - slope(df)*df['Age'].mean()\n    \nn(group_abs)","user":"anonymous","dateUpdated":"2019-07-22T18:42:55+0200","config":{"editorSetting":{"language":"python","editOnDblClick":false,"completionSupport":true,"completionKey":"TAB"},"colWidth":12,"editorMode":"ace/mode/python","fontSize":9,"results":{},"enabled":true},"settings":{"params":{},"forms":{}},"results":{"code":"SUCCESS","msg":[{"type":"TEXT","data":"21.587381898910635\n"}]},"apps":[],"jobName":"paragraph_1563699617473_-1829002637","id":"20190626-114902_768521075","dateCreated":"2019-07-21T11:00:17+0200","dateStarted":"2019-07-22T18:42:55+0200","dateFinished":"2019-07-22T18:42:55+0200","status":"FINISHED","progressUpdateIntervalMs":500,"$$hashKey":"object:6051"},{"text":"%md\n#### 4.- Define a function to calculate the covariance and the correlation of two variables.","user":"anonymous","dateUpdated":"2019-07-21T11:00:17+0200","config":{"tableHide":false,"editorSetting":{"language":"markdown","editOnDblClick":true,"completionSupport":false},"colWidth":12,"editorMode":"ace/mode/markdown","fontSize":9,"editorHide":true,"results":{},"enabled":true},"settings":{"params":{},"forms":{}},"results":{"code":"SUCCESS","msg":[{"type":"HTML","data":"<div class=\"markdown-body\">\n<h4>4.- Define a function to calculate the covariance and the correlation of two variables.</h4>\n</div>"}]},"apps":[],"jobName":"paragraph_1563699617474_-1510337827","id":"20190626-114708_653238055","dateCreated":"2019-07-21T11:00:17+0200","status":"READY","errorMessage":"","progressUpdateIntervalMs":500,"$$hashKey":"object:6052"},{"text":"def covar(df):\n    covar = 0\n    for i in range(len(df['Age'])):\n        covar += (df['Age'][i]-df['Age'].mean())*(df['Absences'][i]-df['Absences'].mean())\n    return covar/len(df['Age'])\n\ndef correl(df):\n    return covar(df)/(df['Age'].std()*df['Absences'].std())\n    \nprint(covar(group_abs),correl(group_abs))\n    ","user":"anonymous","dateUpdated":"2019-07-22T18:49:44+0200","config":{"editorSetting":{"language":"python","editOnDblClick":false,"completionSupport":true,"completionKey":"TAB"},"colWidth":12,"editorMode":"ace/mode/python","fontSize":9,"results":{},"enabled":true},"settings":{"params":{},"forms":{}},"results":{"code":"SUCCESS","msg":[{"type":"TEXT","data":"(-51.93000000000001, -0.8392890683232912)\n"}]},"apps":[],"jobName":"paragraph_1563699617474_1063541987","id":"20190626-114904_1010319335","dateCreated":"2019-07-21T11:00:17+0200","dateStarted":"2019-07-22T18:49:44+0200","dateFinished":"2019-07-22T18:49:44+0200","status":"FINISHED","progressUpdateIntervalMs":500,"$$hashKey":"object:6053"},{"text":"%md\n#### 5.- Use the function you defined in step 4 to calculate the covariance and the correlation of `Age` and `Absences`. Compare them and comment.","user":"anonymous","dateUpdated":"2019-07-21T11:00:17+0200","config":{"tableHide":false,"editorSetting":{"language":"markdown","editOnDblClick":true,"completionSupport":false},"colWidth":12,"editorMode":"ace/mode/markdown","fontSize":9,"editorHide":true,"results":{},"enabled":true},"settings":{"params":{},"forms":{}},"results":{"code":"SUCCESS","msg":[{"type":"HTML","data":"<div class=\"markdown-body\">\n<h4>5.- Use the function you defined in step 4 to calculate the covariance and the correlation of <code>Age</code> and <code>Absences</code>. Compare them and comment.</h4>\n</div>"}]},"apps":[],"jobName":"paragraph_1563699617475_-1624451743","id":"20190626-114710_745091387","dateCreated":"2019-07-21T11:00:17+0200","status":"READY","errorMessage":"","progressUpdateIntervalMs":500,"$$hashKey":"object:6054"},{"text":"print(covar(group_abs),correl(group_abs))\n#Strong negative correlation","user":"anonymous","dateUpdated":"2019-07-22T18:50:09+0200","config":{"editorSetting":{"language":"python","editOnDblClick":false,"completionSupport":true,"completionKey":"TAB"},"colWidth":12,"editorMode":"ace/mode/python","fontSize":9,"results":{},"enabled":true},"settings":{"params":{},"forms":{}},"results":{"code":"SUCCESS","msg":[{"type":"TEXT","data":"(-51.93000000000001, -0.8392890683232912)\n"}]},"apps":[],"jobName":"paragraph_1563699617476_364618699","id":"20190626-114905_1561094477","dateCreated":"2019-07-21T11:00:17+0200","dateStarted":"2019-07-22T18:50:09+0200","dateFinished":"2019-07-22T18:50:09+0200","status":"FINISHED","progressUpdateIntervalMs":500,"$$hashKey":"object:6055"},{"text":"%md\n#### 6.- Summarize your results, interpret them and give some insights. Can you confirm that the age is an indicator of absenteeism?","user":"anonymous","dateUpdated":"2019-07-21T11:00:17+0200","config":{"tableHide":false,"editorSetting":{"language":"markdown","editOnDblClick":true,"completionSupport":false},"colWidth":12,"editorMode":"ace/mode/markdown","fontSize":9,"editorHide":true,"results":{},"enabled":true},"settings":{"params":{},"forms":{}},"results":{"code":"SUCCESS","msg":[{"type":"HTML","data":"<div class=\"markdown-body\">\n<h4>6.- Summarize your results, interpret them and give some insights. Can you confirm that the age is an indicator of absenteeism?</h4>\n</div>"}]},"apps":[],"jobName":"paragraph_1563699617477_-723002776","id":"20190626-114712_1568710553","dateCreated":"2019-07-21T11:00:17+0200","status":"READY","errorMessage":"","progressUpdateIntervalMs":500,"$$hashKey":"object:6056"},{"text":"# We can confirm the trend that the younger the employee, the more absences it commits.","user":"anonymous","dateUpdated":"2019-07-22T18:50:56+0200","config":{"editorSetting":{"language":"python","editOnDblClick":false,"completionSupport":true,"completionKey":"TAB"},"colWidth":12,"editorMode":"ace/mode/python","fontSize":9,"results":{},"enabled":true},"settings":{"params":{},"forms":{}},"apps":[],"jobName":"paragraph_1563699617478_625306676","id":"20190626-114909_2074195551","dateCreated":"2019-07-21T11:00:17+0200","status":"READY","errorMessage":"","progressUpdateIntervalMs":500,"$$hashKey":"object:6057"},{"text":"%md \n## Challenge 2\n\nGood Ironhackers stay in campus on Fridays for Ironbeers. You suspect that the more people you tell to stay, the most likely it is that they don't. You want to know if you are the reason why people don't stay so you decide to do an analysis. \n\nX is the number of people that you told to stay and Y is the number of people that actually stayed.\n\n| X | Y |\n|---|---|\n| 1 | 1 |\n| 3 | 2 |\n| 4 | 4 |\n| 6 | 4 |\n| 8 | 5 |\n| 9 | 7 |\n| 11 |8 |\n| 14 | 9 |\n\nUse the following command to create a dataframe with the data about Ironbeers attendance: ","user":"anonymous","dateUpdated":"2019-07-21T11:00:17+0200","config":{"tableHide":false,"editorSetting":{"language":"markdown","editOnDblClick":true,"completionSupport":false},"colWidth":12,"editorMode":"ace/mode/markdown","fontSize":9,"editorHide":true,"results":{},"enabled":true},"settings":{"params":{},"forms":{}},"results":{"code":"SUCCESS","msg":[{"type":"HTML","data":"<div class=\"markdown-body\">\n<h2>Challenge 2</h2>\n<p>Good Ironhackers stay in campus on Fridays for Ironbeers. You suspect that the more people you tell to stay, the most likely it is that they don&rsquo;t. You want to know if you are the reason why people don&rsquo;t stay so you decide to do an analysis. </p>\n<p>X is the number of people that you told to stay and Y is the number of people that actually stayed.</p>\n<table>\n  <thead>\n    <tr>\n      <th>X </th>\n      <th>Y </th>\n    </tr>\n  </thead>\n  <tbody>\n    <tr>\n      <td>1 </td>\n      <td>1 </td>\n    </tr>\n    <tr>\n      <td>3 </td>\n      <td>2 </td>\n    </tr>\n    <tr>\n      <td>4 </td>\n      <td>4 </td>\n    </tr>\n    <tr>\n      <td>6 </td>\n      <td>4 </td>\n    </tr>\n    <tr>\n      <td>8 </td>\n      <td>5 </td>\n    </tr>\n    <tr>\n      <td>9 </td>\n      <td>7 </td>\n    </tr>\n    <tr>\n      <td>11 </td>\n      <td>8 </td>\n    </tr>\n    <tr>\n      <td>14 </td>\n      <td>9 </td>\n    </tr>\n  </tbody>\n</table>\n<p>Use the following command to create a dataframe with the data about Ironbeers attendance:</p>\n</div>"}]},"apps":[],"jobName":"paragraph_1563699617479_508834303","id":"20190626-152119_908118441","dateCreated":"2019-07-21T11:00:17+0200","status":"READY","errorMessage":"","progressUpdateIntervalMs":500,"$$hashKey":"object:6058"},{"text":"ironbeers_df = pd.DataFrame({'X': [1,3,4,6,8,9,11,14], 'Y': [1,2,4,4,5,7,8,9]})","user":"anonymous","dateUpdated":"2019-07-22T18:50:57+0200","config":{"editorSetting":{"language":"python","editOnDblClick":false,"completionSupport":true,"completionKey":"TAB"},"colWidth":12,"editorMode":"ace/mode/python","fontSize":9,"results":{},"enabled":true},"settings":{"params":{},"forms":{}},"results":{"code":"SUCCESS","msg":[]},"apps":[],"jobName":"paragraph_1563699617480_-2142377066","id":"20190626-152857_1407473295","dateCreated":"2019-07-21T11:00:17+0200","dateStarted":"2019-07-22T18:50:57+0200","dateFinished":"2019-07-22T18:50:57+0200","status":"FINISHED","progressUpdateIntervalMs":500,"$$hashKey":"object:6059"},{"text":"%md\n#### 1.- Calculate the covariance and the correlation of `X` and `Y`. Comment on the results. ","user":"anonymous","dateUpdated":"2019-07-21T11:00:17+0200","config":{"tableHide":false,"editorSetting":{"language":"markdown","editOnDblClick":true,"completionSupport":false},"colWidth":12,"editorMode":"ace/mode/markdown","fontSize":9,"editorHide":true,"results":{},"enabled":true},"settings":{"params":{},"forms":{}},"results":{"code":"SUCCESS","msg":[{"type":"HTML","data":"<div class=\"markdown-body\">\n<h4>1.- Calculate the covariance and the correlation of <code>X</code> and <code>Y</code>. Comment on the results.</h4>\n</div>"}]},"apps":[],"jobName":"paragraph_1563699617481_1436982207","id":"20190626-152909_1076880974","dateCreated":"2019-07-21T11:00:17+0200","status":"READY","errorMessage":"","progressUpdateIntervalMs":500,"$$hashKey":"object:6060"},{"text":"print(ironbeers_df.cov()['X']['Y'], ironbeers_df.corr()['X']['Y'])","user":"anonymous","dateUpdated":"2019-07-22T18:56:30+0200","config":{"editorSetting":{"language":"python","editOnDblClick":false,"completionSupport":true,"completionKey":"TAB"},"colWidth":12,"editorMode":"ace/mode/python","fontSize":9,"results":{},"enabled":true},"settings":{"params":{},"forms":{}},"results":{"code":"SUCCESS","msg":[{"type":"TEXT","data":"(12.0, 0.9770084209183943)\n"}]},"apps":[],"jobName":"paragraph_1563699617483_107099560","id":"20190626-154852_2021527106","dateCreated":"2019-07-21T11:00:17+0200","dateStarted":"2019-07-22T18:56:30+0200","dateFinished":"2019-07-22T18:56:30+0200","status":"FINISHED","progressUpdateIntervalMs":500,"$$hashKey":"object:6061"},{"text":"%md\n#### 2.- Plot the scatter chart of `X` and `Y`. Comment on the results.","user":"anonymous","dateUpdated":"2019-07-21T11:00:17+0200","config":{"tableHide":false,"editorSetting":{"language":"markdown","editOnDblClick":true,"completionSupport":false},"colWidth":12,"editorMode":"ace/mode/markdown","fontSize":9,"editorHide":true,"results":{},"enabled":true},"settings":{"params":{},"forms":{}},"results":{"code":"SUCCESS","msg":[{"type":"HTML","data":"<div class=\"markdown-body\">\n<h4>2.- Plot the scatter chart of <code>X</code> and <code>Y</code>. Comment on the results.</h4>\n</div>"}]},"apps":[],"jobName":"paragraph_1563699617487_1078721401","id":"20190626-153325_608344445","dateCreated":"2019-07-21T11:00:17+0200","status":"READY","errorMessage":"","progressUpdateIntervalMs":500,"$$hashKey":"object:6062"},{"text":"%sql\nSELECT * FROM ironbeers_df","user":"anonymous","dateUpdated":"2019-07-22T18:57:57+0200","config":{"colWidth":12,"fontSize":9,"enabled":true,"results":{"0":{"graph":{"mode":"scatterChart","height":300,"optionOpen":false,"setting":{"table":{"tableGridState":{},"tableColumnTypeState":{"names":{"X":"string","Y":"string"},"updated":false},"tableOptionSpecHash":"[{\"name\":\"useFilter\",\"valueType\":\"boolean\",\"defaultValue\":false,\"widget\":\"checkbox\",\"description\":\"Enable filter for columns\"},{\"name\":\"showPagination\",\"valueType\":\"boolean\",\"defaultValue\":false,\"widget\":\"checkbox\",\"description\":\"Enable pagination for better navigation\"},{\"name\":\"showAggregationFooter\",\"valueType\":\"boolean\",\"defaultValue\":false,\"widget\":\"checkbox\",\"description\":\"Enable a footer for displaying aggregated values\"}]","tableOptionValue":{"useFilter":false,"showPagination":false,"showAggregationFooter":false},"updated":false,"initialized":false}},"commonSetting":{}},"helium":{}}},"editorSetting":{"language":"sql","editOnDblClick":false,"completionSupport":false,"completionKey":"TAB"},"editorMode":"ace/mode/sql"},"settings":{"params":{},"forms":{}},"results":{"code":"SUCCESS","msg":[{"type":"TABLE","data":"X\tY\n1\t1\n3\t2\n4\t4\n6\t4\n8\t5\n9\t7\n11\t8\n14\t9\n"}]},"apps":[],"jobName":"paragraph_1563814651801_-382749632","id":"20190722-185731_1229230433","dateCreated":"2019-07-22T18:57:31+0200","dateStarted":"2019-07-22T18:57:46+0200","dateFinished":"2019-07-22T18:57:46+0200","status":"FINISHED","progressUpdateIntervalMs":500,"$$hashKey":"object:6063"},{"text":"%md\n#### 3.- Calculate the regression line for `X` and `Y`. Commment on the results.","user":"anonymous","dateUpdated":"2019-07-21T11:00:17+0200","config":{"tableHide":false,"editorSetting":{"language":"markdown","editOnDblClick":true,"completionSupport":false},"colWidth":12,"editorMode":"ace/mode/markdown","fontSize":9,"editorHide":true,"results":{},"enabled":true},"settings":{"params":{},"forms":{}},"results":{"code":"SUCCESS","msg":[{"type":"HTML","data":"<div class=\"markdown-body\">\n<h4>3.- Calculate the regression line for <code>X</code> and <code>Y</code>. Commment on the results.</h4>\n</div>"}]},"apps":[],"jobName":"paragraph_1563699617490_-951837783","id":"20190626-153328_1152788064","dateCreated":"2019-07-21T11:00:17+0200","status":"READY","errorMessage":"","progressUpdateIntervalMs":500,"$$hashKey":"object:6064"},{"text":"print(ironbeers_df.corr()['X']['Y'] * (ironbeers_df['Y'].std()/ironbeers_df['X'].std()), ironbeers_df['Y'].mean() -(ironbeers_df.corr()['X']['Y'] * (ironbeers_df['Y'].std()/ironbeers_df['X'].std()))*ironbeers_df['X'].mean())","user":"anonymous","dateUpdated":"2019-07-22T19:03:28+0200","config":{"editorSetting":{"language":"python","editOnDblClick":false,"completionSupport":true,"completionKey":"TAB"},"colWidth":12,"editorMode":"ace/mode/python","fontSize":9,"results":{"0":{"graph":{"mode":"lineChart","height":300,"optionOpen":false,"setting":{"table":{"tableGridState":{},"tableColumnTypeState":{"names":{"X":"string","Y":"string"},"updated":false},"tableOptionSpecHash":"[{\"name\":\"useFilter\",\"valueType\":\"boolean\",\"defaultValue\":false,\"widget\":\"checkbox\",\"description\":\"Enable filter for columns\"},{\"name\":\"showPagination\",\"valueType\":\"boolean\",\"defaultValue\":false,\"widget\":\"checkbox\",\"description\":\"Enable pagination for better navigation\"},{\"name\":\"showAggregationFooter\",\"valueType\":\"boolean\",\"defaultValue\":false,\"widget\":\"checkbox\",\"description\":\"Enable a footer for displaying aggregated values\"}]","tableOptionValue":{"useFilter":false,"showPagination":false,"showAggregationFooter":false},"updated":false,"initialized":false},"lineChart":{"rotate":{"degree":"-45"},"xLabelStatus":"default"}},"commonSetting":{},"keys":[{"name":"X","index":0,"aggr":"sum"}],"groups":[],"values":[{"name":"Y","index":1,"aggr":"sum"}]},"helium":{}}},"enabled":true},"settings":{"params":{},"forms":{}},"results":{"code":"SUCCESS","msg":[{"type":"TEXT","data":"(0.6363636363636365, 0.545454545454545)\n"}]},"apps":[],"jobName":"paragraph_1563699617491_1494494223","id":"20190626-204752_1693039948","dateCreated":"2019-07-21T11:00:17+0200","dateStarted":"2019-07-22T19:03:28+0200","dateFinished":"2019-07-22T19:03:28+0200","status":"FINISHED","progressUpdateIntervalMs":500,"$$hashKey":"object:6065"},{"text":"%md\n#### 4.- What is your conclusion? Are you the reason why people is not staying on Fridays?","user":"anonymous","dateUpdated":"2019-07-21T11:00:17+0200","config":{"tableHide":false,"editorSetting":{"language":"markdown","editOnDblClick":true,"completionSupport":false},"colWidth":12,"editorMode":"ace/mode/markdown","fontSize":9,"editorHide":true,"results":{},"enabled":true},"settings":{"params":{},"forms":{}},"results":{"code":"SUCCESS","msg":[{"type":"HTML","data":"<div class=\"markdown-body\">\n<h4>4.- What is your conclusion? Are you the reason why people is not staying on Fridays?</h4>\n</div>"}]},"apps":[],"jobName":"paragraph_1563699617492_18994162","id":"20190626-153327_407939418","dateCreated":"2019-07-21T11:00:17+0200","status":"READY","errorMessage":"","progressUpdateIntervalMs":500,"$$hashKey":"object:6066"},{"text":"'''Yes, more insistance results in more people as there is a great correlation.'''","user":"anonymous","dateUpdated":"2019-07-22T19:04:16+0200","config":{"editorSetting":{"language":"python","editOnDblClick":false,"completionSupport":true,"completionKey":"TAB"},"colWidth":12,"editorMode":"ace/mode/python","fontSize":9,"results":{},"enabled":true},"settings":{"params":{},"forms":{}},"results":{"code":"SUCCESS","msg":[{"type":"TEXT","data":"'Yes, more insistance results in more people as there is a great correlation.'\n"}]},"apps":[],"jobName":"paragraph_1563699617493_-1607615670","id":"20190626-153330_1853969000","dateCreated":"2019-07-21T11:00:17+0200","dateStarted":"2019-07-22T19:04:16+0200","dateFinished":"2019-07-22T19:04:16+0200","status":"FINISHED","progressUpdateIntervalMs":500,"$$hashKey":"object:6067"},{"text":"%md\n## Bonus Challenge: Error Analysis\n\nYou are going to do an analysis to check whether two random variables fit into a linear regression or not.\n\nIn this challenge, you are asked to do an error analysis using the data in **challenge 2**. An \"error\" is the difference between the expected value of an observation (the regression line value) and the actual value.\n\n#### 1.- First create a new column `expected_Y` in `ironbeers_df` to store the expected `Y` value for each `X`.\n**Hint**: You get the expected `Y` by evaluating the regression line for each `X`.","user":"anonymous","dateUpdated":"2019-07-21T11:00:17+0200","config":{"tableHide":false,"editorSetting":{"language":"markdown","editOnDblClick":true,"completionSupport":false},"colWidth":12,"editorMode":"ace/mode/markdown","fontSize":9,"editorHide":true,"results":{},"enabled":true},"settings":{"params":{},"forms":{}},"results":{"code":"SUCCESS","msg":[{"type":"HTML","data":"<div class=\"markdown-body\">\n<h2>Bonus Challenge: Error Analysis</h2>\n<p>You are going to do an analysis to check whether two random variables fit into a linear regression or not.</p>\n<p>In this challenge, you are asked to do an error analysis using the data in <strong>challenge 2</strong>. An &ldquo;error&rdquo; is the difference between the expected value of an observation (the regression line value) and the actual value.</p>\n<h4>1.- First create a new column <code>expected_Y</code> in <code>ironbeers_df</code> to store the expected <code>Y</code> value for each <code>X</code>.</h4>\n<p><strong>Hint</strong>: You get the expected <code>Y</code> by evaluating the regression line for each <code>X</code>.</p>\n</div>"}]},"apps":[],"jobName":"paragraph_1563699617494_230451665","id":"20190626-205055_706998840","dateCreated":"2019-07-21T11:00:17+0200","status":"READY","errorMessage":"","progressUpdateIntervalMs":500,"$$hashKey":"object:6068"},{"text":"","user":"anonymous","dateUpdated":"2019-07-21T11:00:17+0200","config":{"editorSetting":{"language":"python","editOnDblClick":false,"completionSupport":true,"completionKey":"TAB"},"colWidth":12,"editorMode":"ace/mode/python","fontSize":9,"results":{},"enabled":true},"settings":{"params":{},"forms":{}},"apps":[],"jobName":"paragraph_1563699617494_-1998961082","id":"20190626-211050_943371350","dateCreated":"2019-07-21T11:00:17+0200","status":"READY","errorMessage":"","progressUpdateIntervalMs":500,"$$hashKey":"object:6069"},{"text":"%md\n\n#### 2.- Create a new column `error` in `ironbeers_df` to store the error between the actual and expected values of `Y`. Plot the scatter chart of `X` and `error`.","user":"anonymous","dateUpdated":"2019-07-21T11:00:17+0200","config":{"tableHide":false,"editorSetting":{"language":"markdown","editOnDblClick":true,"completionSupport":false},"colWidth":12,"editorMode":"ace/mode/markdown","fontSize":9,"editorHide":true,"results":{},"enabled":true},"settings":{"params":{},"forms":{}},"results":{"code":"SUCCESS","msg":[{"type":"HTML","data":"<div class=\"markdown-body\">\n<h4>2.- Create a new column <code>error</code> in <code>ironbeers_df</code> to store the error between the actual and expected values of <code>Y</code>. Plot the scatter chart of <code>X</code> and <code>error</code>.</h4>\n</div>"}]},"apps":[],"jobName":"paragraph_1563699617495_161100752","id":"20190626-211051_117697439","dateCreated":"2019-07-21T11:00:17+0200","status":"READY","errorMessage":"","progressUpdateIntervalMs":500,"$$hashKey":"object:6070"},{"text":"","user":"anonymous","dateUpdated":"2019-07-21T11:00:17+0200","config":{"editorSetting":{"language":"python","editOnDblClick":false,"completionSupport":true,"completionKey":"TAB"},"colWidth":12,"editorMode":"ace/mode/python","fontSize":9,"results":{"0":{"graph":{"mode":"scatterChart","height":300,"optionOpen":false,"setting":{"table":{"tableGridState":{},"tableColumnTypeState":{"names":{"X":"string","diff":"string"},"updated":false},"tableOptionSpecHash":"[{\"name\":\"useFilter\",\"valueType\":\"boolean\",\"defaultValue\":false,\"widget\":\"checkbox\",\"description\":\"Enable filter for columns\"},{\"name\":\"showPagination\",\"valueType\":\"boolean\",\"defaultValue\":false,\"widget\":\"checkbox\",\"description\":\"Enable pagination for better navigation\"},{\"name\":\"showAggregationFooter\",\"valueType\":\"boolean\",\"defaultValue\":false,\"widget\":\"checkbox\",\"description\":\"Enable a footer for displaying aggregated values\"}]","tableOptionValue":{"useFilter":false,"showPagination":false,"showAggregationFooter":false},"updated":false,"initialized":false}},"commonSetting":{}},"helium":{}}},"enabled":true},"settings":{"params":{},"forms":{}},"apps":[],"jobName":"paragraph_1563699617497_-343753679","id":"20190626-212326_130532268","dateCreated":"2019-07-21T11:00:17+0200","status":"READY","errorMessage":"","progressUpdateIntervalMs":500,"$$hashKey":"object:6071"},{"text":"%md\n#### 3.- The closer the points to zero, the best the actual values fit the linear regression. Comment the plot above. Do you see any particular points with a high error?","user":"anonymous","dateUpdated":"2019-07-21T11:00:17+0200","config":{"tableHide":false,"editorSetting":{"language":"markdown","editOnDblClick":true,"completionSupport":false},"colWidth":12,"editorMode":"ace/mode/markdown","fontSize":9,"editorHide":true,"results":{},"enabled":true},"settings":{"params":{},"forms":{}},"results":{"code":"SUCCESS","msg":[{"type":"HTML","data":"<div class=\"markdown-body\">\n<h4>3.- The closer the points to zero, the best the actual values fit the linear regression. Comment the plot above. Do you see any particular points with a high error?</h4>\n</div>"}]},"apps":[],"jobName":"paragraph_1563699617498_-391302642","id":"20190626-211354_1152941379","dateCreated":"2019-07-21T11:00:17+0200","status":"READY","errorMessage":"","progressUpdateIntervalMs":500,"$$hashKey":"object:6072"},{"text":"","user":"anonymous","dateUpdated":"2019-07-21T11:00:17+0200","config":{"editorSetting":{"language":"python","editOnDblClick":false,"completionSupport":true,"completionKey":"TAB"},"colWidth":12,"editorMode":"ace/mode/python","fontSize":9,"results":{},"enabled":true},"settings":{"params":{},"forms":{}},"apps":[],"jobName":"paragraph_1563699617499_767809926","id":"20190626-213919_665730285","dateCreated":"2019-07-21T11:00:17+0200","status":"READY","errorMessage":"","progressUpdateIntervalMs":500,"$$hashKey":"object:6073"},{"text":"%md\n#### 4.- Remove the points with a high error and recalculate the regression line. ","user":"anonymous","dateUpdated":"2019-07-21T11:00:17+0200","config":{"tableHide":false,"editorSetting":{"language":"markdown","editOnDblClick":true,"completionSupport":false},"colWidth":12,"editorMode":"ace/mode/markdown","fontSize":9,"editorHide":true,"results":{},"enabled":true},"settings":{"params":{},"forms":{}},"results":{"code":"SUCCESS","msg":[{"type":"HTML","data":"<div class=\"markdown-body\">\n<h4>4.- Remove the points with a high error and recalculate the regression line.</h4>\n</div>"}]},"apps":[],"jobName":"paragraph_1563699617500_228608025","id":"20190626-213951_1863990414","dateCreated":"2019-07-21T11:00:17+0200","status":"READY","errorMessage":"","progressUpdateIntervalMs":500,"$$hashKey":"object:6074"},{"text":"","user":"anonymous","dateUpdated":"2019-07-21T11:00:17+0200","config":{"editorSetting":{"language":"python","editOnDblClick":false,"completionSupport":true,"completionKey":"TAB"},"colWidth":12,"editorMode":"ace/mode/python","fontSize":9,"results":{},"enabled":true},"settings":{"params":{},"forms":{}},"apps":[],"jobName":"paragraph_1563699617501_-1901352009","id":"20190626-214055_548357742","dateCreated":"2019-07-21T11:00:17+0200","status":"READY","errorMessage":"","progressUpdateIntervalMs":500,"$$hashKey":"object:6075"},{"text":"%md\n#### 5.- Calculate the correlation. What is happening? Comment the result. ","user":"anonymous","dateUpdated":"2019-07-21T11:00:17+0200","config":{"tableHide":false,"editorSetting":{"language":"markdown","editOnDblClick":true,"completionSupport":false},"colWidth":12,"editorMode":"ace/mode/markdown","fontSize":9,"editorHide":true,"results":{},"enabled":true},"settings":{"params":{},"forms":{}},"results":{"code":"SUCCESS","msg":[{"type":"HTML","data":"<div class=\"markdown-body\">\n<h4>5.- Calculate the correlation. What is happening? Comment the result.</h4>\n</div>"}]},"apps":[],"jobName":"paragraph_1563699617502_-579326752","id":"20190626-214101_161461197","dateCreated":"2019-07-21T11:00:17+0200","status":"READY","errorMessage":"","progressUpdateIntervalMs":500,"$$hashKey":"object:6076"},{"text":"","user":"anonymous","dateUpdated":"2019-07-21T11:00:17+0200","config":{"editorSetting":{"language":"python","editOnDblClick":false,"completionSupport":true,"completionKey":"TAB"},"colWidth":12,"editorMode":"ace/mode/python","fontSize":9,"results":{},"enabled":true},"settings":{"params":{},"forms":{}},"apps":[],"jobName":"paragraph_1563699617503_-1115474903","id":"20190626-214120_1816290913","dateCreated":"2019-07-21T11:00:17+0200","status":"READY","errorMessage":"","progressUpdateIntervalMs":500,"$$hashKey":"object:6077"}],"name":"linear-regression","id":"2EJ9FBV64","noteParams":{},"noteForms":{},"angularObjects":{"md:shared_process":[],"python:shared_process":[],"spark:shared_process":[]},"config":{"isZeppelinNotebookCronEnable":false,"looknfeel":"default","personalizedMode":"false"},"info":{}}